{
  "timestamp": "2025-09-18T21:12:50.500344",
  "task": {
    "cirq_type": "recirq.sky_ground.WHSkyGroundTask",
    "dataset_id": "9_18_25",
    "processor_id": "willow_pink",
    "run_type": "noisy",
    "wh_implementation": "ak",
    "description": "basis_measurement_on_basis_states",
    "n_shots": 10000,
    "qubits": [
      {
        "cirq_type": "GridQubit",
        "row": 5,
        "col": 9
      },
      {
        "cirq_type": "GridQubit",
        "row": 6,
        "col": 9
      },
      {
        "cirq_type": "GridQubit",
        "row": 5,
        "col": 10
      },
      {
        "cirq_type": "GridQubit",
        "row": 6,
        "col": 10
      },
      {
        "cirq_type": "GridQubit",
        "row": 5,
        "col": 11
      },
      {
        "cirq_type": "GridQubit",
        "row": 6,
        "col": 11
      }
    ],
    "d": 4
  },
  "m": [
    0,
    1,
    2,
    3
  ],
  "q": [
    [
      0.9873,
      0.0125,
      0.0178,
      0.0001
    ],
    [
      0.0026,
      0.9765,
      0.0002,
      0.0184
    ],
    [
      0.01,
      0.0001,
      0.9802,
      0.0123
    ],
    [
      0.0001,
      0.0109,
      0.0018,
      0.9692
    ]
  ]
}